santander_python_sdk-0.4.1.dist-info/licenses/LICENCE
santander_sdk/__init__.py
santander_sdk/payment_receipts.py
santander_sdk/pix.py
santander_sdk/transfer_flow.py
santander_sdk/types.py
santander_sdk/api_client/__init__.py
santander_sdk/api_client/auth.py
santander_sdk/api_client/base.py
santander_sdk/api_client/client.py
santander_sdk/api_client/client_configuration.py
santander_sdk/api_client/exceptions.py
santander_sdk/api_client/helpers.py
santander_sdk/api_client/workspaces.py
santander_sdk/typing/receipts_types.py
santander_python_sdk-0.4.1.dist-info/METADATA
santander_python_sdk-0.4.1.dist-info/WHEEL
santander_python_sdk-0.4.1.dist-info/top_level.txt
santander_python_sdk-0.4.1.dist-info/RECORD
