Metadata-Version: 2.4
Name: santander-python-sdk
Version: 0.4.1
Summary: Client não oficial da API do Santander em Python
Author-email: Samuel Rodrigues Coelho <samuel.coelho@buser.com.br>, Erle Carrara <erle.carrara@buser.com.br>, Walison Filipe <walison.filipe@buser.com.br>
Project-URL: homepage, https://github.com/buserbrasil/santander-python-sdk
Project-URL: repository, https://github.com/buserbrasil/santander-python-sdk
Keywords: santander,api,client,python
Classifier: Development Status :: 3 - Alpha
Classifier: Intended Audience :: Developers
Classifier: Topic :: Software Development :: Libraries :: Python Modules
Classifier: License :: OSI Approved :: MIT License
Classifier: Programming Language :: Python :: 3.11
Classifier: Programming Language :: Python :: 3.12
Requires-Python: >=3.11
License-File: LICENCE
Requires-Dist: python-dateutil~=2.0
Requires-Dist: requests>=2
Dynamic: license-file
